[
    {
        "id": 45084,
        "applicationDocumentDetailsList": [
            {
                "id": 30227,
                "activeStatus": "A",
                "modifiedBy": "shivm_user",
                "modifiedDate": "2026-03-19T10:14:17.427",
                "application": 45084,
                "documentType": 54,
                "submittedDate": "2026-03-19",
                "filePath": "shivm_user/2026-03-19/IMG_0003_1773894548894.pdf",
                "encryptedId": "f58ab4021106972ae9a2eb73f757a32b77a805c450828ae6a2f439f362098b44ede2b06ee4e735d5cec8c9279d940f722d466e00563b8f6710bd7ddc3bd8cc8e",
                "fileUrl": "https://www.nepalstock.com.np/api/nots/security/fetchFiles?fileLocation=shivm_user/2026-03-19/IMG_0003_1773894548894.pdf"
            }
        ],
        "newsHeadline": "Resignation of Independent Director  [SHIVM] ",
        "newsBody": "",
        "addedDate": "2026-03-19T10:14:17.413",
        "newsSource": "Board of Director Meeting",
        "modifiedDate": "2026-03-19T10:15:07.103",
        "approvedDate": null,
        "symbol": "SHIVM"
    },
    {
        "id": 45077,
        "applicationDocumentDetailsList": [
            {
                "id": 30219,
                "activeStatus": "A",
                "modifiedBy": "slbsl_user",
                "modifiedDate": "2026-03-18T10:23:59.027",
                "application": 45077,
                "documentType": 54,
                "submittedDate": "2026-03-18",
                "filePath": "Samudayik_Laghubitta_Bittiya_Sanstha_Limited/Company News/2026-03-18/Notice of 12th AGM published in Nepal Samachar Patra 2082-12-04_1773808724893.jpeg",
                "encryptedId": "61b3152df82044608b0bbf5ea40f66b6d79651ceb89c7f36ee1dc57e3b8fbd0441668d89cc00a8d725dc692e5465ac15c51bbf7904c73a9bcda10884cfab7b74",
                "fileUrl": "https://www.nepalstock.com.np/api/nots/security/fetchFiles?fileLocation=Samudayik_Laghubitta_Bittiya_Sanstha_Limited/Company%20News/2026-03-18/Notice%20of%2012th%20AGM%20published%20in%20Nepal%20Samachar%20Patra%202082-12-04_1773808724893.jpeg"
            },
            {
                "id": 30220,
                "activeStatus": "A",
                "modifiedBy": "slbsl_user",
                "modifiedDate": "2026-03-18T10:23:59.027",
                "application": 45077,
                "documentType": 54,
                "submittedDate": "2026-03-18",
                "filePath": "Samudayik_Laghubitta_Bittiya_Sanstha_Limited/Company News/2026-03-18/Information about 12th AGM to Nepal stock exchange_1773808625167.PDF",
                "encryptedId": "da69895b55080af34e1700252f1962ee61ed0e8b4ccd31c199f1c402526a25acb3c8be2cec75651fcd790c26b929b599f35062a778603a790e8f1ec48e2063c2",
                "fileUrl": "https://www.nepalstock.com.np/api/nots/security/fetchFiles?fileLocation=Samudayik_Laghubitta_Bittiya_Sanstha_Limited/Company%20News/2026-03-18/Information%20about%2012th%20AGM%20to%20Nepal%20stock%20exchange_1773808625167.PDF"
            }
        ],
        "newsHeadline": "12th AGM Notice of Samudayik Laghubitta [SLBSL] ",
        "newsBody": "Annual General Meeting of SLBSL\nFiscal Year: 2081-2082\nAGM Type: AGM\nAGM Date: 4/10/2026\nAGM No: 12\nBook Close Date: 4/1/2026",
        "addedDate": "2026-03-18T10:23:59.023",
        "newsSource": "Notice Published in Nepal Samachar Patra 2082-12-4",
        "modifiedDate": "2026-03-19T10:02:55.727",
        "approvedDate": null,
        "symbol": "SLBSL"
    },
    {
        "id": 45076,
        "applicationDocumentDetailsList": [
            {
                "id": 30218,
                "activeStatus": "A",
                "modifiedBy": "nmbmf_user",
                "modifiedDate": "2026-03-18T10:11:27.563",
                "application": 45076,
                "documentType": 54,
                "submittedDate": "2026-03-18",
                "filePath": "nmbmf_user/2026-03-18/Information About 13th AGM_1773807966168.PDF",
                "encryptedId": "2a2ff5abf876169f7bf8a6309ba5ea2c36764791eb0dc4d6b97ae0abdc8f9f56f437cd1a41cc3bcb54944a7dfbf8ef0af514b92b7d2e20da7fa80687bd55f2c4",
                "fileUrl": "https://www.nepalstock.com.np/api/nots/security/fetchFiles?fileLocation=nmbmf_user/2026-03-18/Information%20About%2013th%20AGM_1773807966168.PDF"
            }
        ],
        "newsHeadline": "Information About 13th AGM of NMBMF  [NMBMF] ",
        "newsBody": "Annual General Meeting of NMBMF\nFiscal Year: 2081-2082\nAGM Type: AGM\nAGM Date: 4/8/2026\nAGM No: 13\nBook Close Date: 3/31/2026",
        "addedDate": "2026-03-18T10:11:27.537",
        "newsSource": "NMBMF",
        "modifiedDate": "2026-03-19T10:02:11.493",
        "approvedDate": null,
        "symbol": "NMBMF"
    },
    {
        "id": 45075,
        "applicationDocumentDetailsList": [
            {
                "id": 30217,
                "activeStatus": "A",
                "modifiedBy": "pli_user",
                "modifiedDate": "2026-03-17T17:27:00.987",
                "application": 45075,
                "documentType": 54,
                "submittedDate": "2026-03-17",
                "filePath": "Prabhu__Life_Insurance_Limited/Company News/2026-03-17/Special AGM_1773747699625.pdf",
                "encryptedId": "b65d23d58e926031e734294ad538ef8b1b98f46b99ad797c33ce9ca30f68aac387ba2c5a176479e3f45575aabad60a48dd9740414b176686488f51c9dfd1735b",
                "fileUrl": "https://www.nepalstock.com.np/api/nots/security/fetchFiles?fileLocation=Prabhu__Life_Insurance_Limited/Company%20News/2026-03-17/Special%20AGM_1773747699625.pdf"
            }
        ],
        "newsHeadline": "Special General Meeting [PMLI] ",
        "newsBody": "<p>The Company 38th Board meeting held on 2082/12/3 at 4:00 PM has decided to call special general meeting for conversion of 10% promoter share</p>",
        "addedDate": "2026-03-17T17:27:00.983",
        "newsSource": "38th Board Meeting Decision",
        "modifiedDate": "2026-03-19T10:01:33.553",
        "approvedDate": null,
        "symbol": "PMLI"
    },
    {
        "id": 45070,
        "applicationDocumentDetailsList": [
            {
                "id": 30215,
                "activeStatus": "A",
                "modifiedBy": "river_user",
                "modifiedDate": "2026-03-17T15:50:22.747",
                "application": 45070,
                "documentType": 54,
                "submittedDate": "2026-03-17",
                "filePath": "River_Falls_power_Limited/Company News/2026-03-17/Auditor Appointment_1773741896891.pdf",
                "encryptedId": "8faf5e75c7227f15acfed4745d81960a0b27e03e9016598bb73809d0e06efab74bfe2d8f547923c74d6636a3f740faaf396d30a5f5687382947d69d8d9eddc9a",
                "fileUrl": "https://www.nepalstock.com.np/api/nots/security/fetchFiles?fileLocation=River_Falls_power_Limited/Company%20News/2026-03-17/Auditor%20Appointment_1773741896891.pdf"
            }
        ],
        "newsHeadline": "\u0932\u0947\u0916\u093e \u092a\u0930\u093f\u0915\u094d\u0937\u0915 \u0928\u093f\u092f\u0942\u0915\u094d\u0924\u093f \u0917\u0930\u0947\u0915\u093e\u0947 \u091c\u093e\u0928\u0915\u093e\u0930\u0940 \u0938\u092e\u094d\u092c\u0928\u094d\u0927\u092e\u093e [RFPL] ",
        "newsBody": "<p>\u0932\u0947\u0916\u093e \u092a\u0930\u093f\u0915\u094d\u0937\u0915 \u0928\u093f\u092f\u0942\u0915\u094d\u0924\u093f \u0917\u0930\u0947\u0915\u093e\u0947 \u091c\u093e\u0928\u0915\u093e\u0930\u0940 \u0938\u092e\u094d\u092c\u0928\u094d\u0927\u092e\u093e</p>",
        "addedDate": "2026-03-17T15:50:22.743",
        "newsSource": "\u0932\u0947\u0916\u093e \u092a\u0930\u093f\u0915\u094d\u0937\u0915 \u0928\u093f\u092f\u0942\u0915\u094d\u0924\u093f \u0917\u0930\u0947\u0915\u093e\u0947 \u0938\u092e\u094d\u092c\u0928\u094d\u0927\u092e\u093e",
        "modifiedDate": "2026-03-17T15:52:30.173",
        "approvedDate": null,
        "symbol": "RFPL"
    },
    {
        "id": 45066,
        "applicationDocumentDetailsList": [
            {
                "id": 30214,
                "activeStatus": "A",
                "modifiedBy": "upper_user",
                "modifiedDate": "2026-03-17T15:05:53.567",
                "application": 45066,
                "documentType": 54,
                "submittedDate": "2026-03-17",
                "filePath": "upper_user/2026-03-17/2082-12-02- Appointment of A CEO_1773739229778.pdf",
                "encryptedId": "d1af2be99d5e88b71ada718a0fe090d56e23a3bbc11a9d1dddc99637367ade4db9acb02b800af75380829d20dcb863ffb62736b154a094b0335bdff7fef2b517",
                "fileUrl": "https://www.nepalstock.com.np/api/nots/security/fetchFiles?fileLocation=upper_user/2026-03-17/2082-12-02-%20Appointment%20of%20A%20CEO_1773739229778.pdf"
            }
        ],
        "newsHeadline": "Appointment of A.CEO [UPPER] ",
        "newsBody": "<p>Please find the attached file for more information.</p>",
        "addedDate": "2026-03-17T15:05:53.563",
        "newsSource": "UPPER",
        "modifiedDate": "2026-03-17T15:34:39.11",
        "approvedDate": null,
        "symbol": "UPPER"
    },
    {
        "id": 45048,
        "applicationDocumentDetailsList": [
            {
                "id": 30190,
                "activeStatus": "A",
                "modifiedBy": "nifra_user",
                "modifiedDate": "2026-03-17T10:37:44.657",
                "application": 45048,
                "documentType": 54,
                "submittedDate": "2026-03-17",
                "filePath": "Nepal_Infrastructure_Bank_Limited/Company News/2026-03-17/Director Resignation and Resignation_NIFRA_1773723145681.pdf",
                "encryptedId": "b5762b4bd83a44339130eee2e4740b466dd0c24bb6029451e86b680d7f225af70ca4da5b1ce8529a255f258a5f8f0830102105fb4fed6c4c8cf73a915a3abf49",
                "fileUrl": "https://www.nepalstock.com.np/api/nots/security/fetchFiles?fileLocation=Nepal_Infrastructure_Bank_Limited/Company%20News/2026-03-17/Director%20Resignation%20and%20Resignation_NIFRA_1773723145681.pdf"
            }
        ],
        "newsHeadline": "Director Resignation and Appointment [NIFRA] ",
        "newsBody": "<p>Director Resignation and Appointment-NIFRA</p>",
        "addedDate": "2026-03-17T10:37:44.653",
        "newsSource": "NIFRA",
        "modifiedDate": "2026-03-17T10:40:06.71",
        "approvedDate": null,
        "symbol": "NIFRA"
    },
    {
        "id": 45046,
        "applicationDocumentDetailsList": [
            {
                "id": 30188,
                "activeStatus": "A",
                "modifiedBy": "jslbb_user",
                "modifiedDate": "2026-03-17T08:42:42.963",
                "application": 45046,
                "documentType": 54,
                "submittedDate": "2026-03-17",
                "filePath": "jslbb_user/2026-03-17/AGM_ Minute_ 15th_1773716255182.pdf",
                "encryptedId": "48bb25834325350ee051dbcb14a163988c2041497b90203c4f3aee003a7c40f2fca9a3cc3a8bcd161cec7a3148c5303a3be9992b9eebdc059e2891e5bc45d3bd",
                "fileUrl": "https://www.nepalstock.com.np/api/nots/security/fetchFiles?fileLocation=jslbb_user/2026-03-17/AGM_%20Minute_%2015th_1773716255182.pdf"
            }
        ],
        "newsHeadline": "15th AGM Minute FY 2081.082 [JSLBB] ",
        "newsBody": "",
        "addedDate": "2026-03-17T08:42:42.947",
        "newsSource": "JSLBSL",
        "modifiedDate": "2026-03-17T10:02:56.783",
        "approvedDate": null,
        "symbol": "JSLBB"
    },
    {
        "id": 45034,
        "applicationDocumentDetailsList": [
            {
                "id": 30179,
                "activeStatus": "A",
                "modifiedBy": "nil_user",
                "modifiedDate": "2026-03-16T13:31:29.903",
                "application": 45034,
                "documentType": 54,
                "submittedDate": "2026-03-16",
                "filePath": "nil_user/2026-03-16/Letter to NEPSE_30th AGM Minute_1773647106110.pdf",
                "encryptedId": "d8915f8f882d826d62b54561172eb20c6f333400df7d53fc7d986a9b7c596f8acdbf5a19b253692836cf16c5f993960f28eb2e3ab2daaeaddb3f0e8aaa1aa23c",
                "fileUrl": "https://www.nepalstock.com.np/api/nots/security/fetchFiles?fileLocation=nil_user/2026-03-16/Letter%20to%20NEPSE_30th%20AGM%20Minute_1773647106110.pdf"
            }
        ],
        "newsHeadline": "30th AGM Minute [NIL] ",
        "newsBody": "",
        "addedDate": "2026-03-16T13:31:29.897",
        "newsSource": "30th AGM Minute",
        "modifiedDate": "2026-03-16T13:37:15.667",
        "approvedDate": null,
        "symbol": "NIL"
    },
    {
        "id": 45027,
        "applicationDocumentDetailsList": [
            {
                "id": 30175,
                "activeStatus": "A",
                "modifiedBy": "smhl_user",
                "modifiedDate": "2026-03-16T10:01:27.93",
                "application": 45027,
                "documentType": 54,
                "submittedDate": "2026-03-16",
                "filePath": "Super_Madi_Hydopower_Limited/Company News/2026-03-16/Information Letter-SMHL-2082-12-02_1773634549326.pdf",
                "encryptedId": "0d5afec019d443e35bcd265afa972a3839c19d0f2c88902673f3111f5396496a3fb74bd88eb310a71ee7423b275f5895a028a6dcaef6e347a88a0da5fc402ccf",
                "fileUrl": "https://www.nepalstock.com.np/api/nots/security/fetchFiles?fileLocation=Super_Madi_Hydopower_Limited/Company%20News/2026-03-16/Information%20Letter-SMHL-2082-12-02_1773634549326.pdf"
            }
        ],
        "newsHeadline": "Appointment of Chairman and Director  [SMHL] ",
        "newsBody": "<p>Appointment of Chairman and Director </p>",
        "addedDate": "2026-03-16T10:01:27.923",
        "newsSource": "SMHL ",
        "modifiedDate": "2026-03-16T10:09:30.003",
        "approvedDate": null,
        "symbol": "SMHL"
    },
    {
        "id": 45026,
        "applicationDocumentDetailsList": [
            {
                "id": 30174,
                "activeStatus": "A",
                "modifiedBy": "madhya_user",
                "modifiedDate": "2026-03-15T21:48:21.507",
                "application": 45026,
                "documentType": 54,
                "submittedDate": "2026-03-15",
                "filePath": "madhya_user/2026-03-15/New Chairmanship FJR_1773590585358.pdf",
                "encryptedId": "7c7e96396f8e6ca118eba7ba419afb7eb4491870363d1ad69ad7b7a2b4463212c9ea22aedad12e90a2d3b9d30c85a37a7e3908a1bf09af50d0d282bd0ef88d50",
                "fileUrl": "https://www.nepalstock.com.np/api/nots/security/fetchFiles?fileLocation=madhya_user/2026-03-15/New%20Chairmanship%20FJR_1773590585358.pdf"
            }
        ],
        "newsHeadline": "New Chairmanship [MBJC] ",
        "newsBody": "<p>The 391st Board Meeting of the company, held on 2082.12.01 (March 15, 2026) has unanimously appointed Mr. Fanendra Raj Joshi as its new Chairman. Mr. Joshi, a nominee of Chilime Hydropower Co. Ltd., succeeds Mr. Tulasi Ram Dhakal, who resigned from the chairmanship due to personal commitments but will continue to serve as a Board Member. The transition is effective as of today's board resolution.</p>",
        "addedDate": "2026-03-15T21:48:21.503",
        "newsSource": "391st BOD dated 2082.12.01",
        "modifiedDate": "2026-03-16T10:09:08.617",
        "approvedDate": null,
        "symbol": "MBJC"
    },
    {
        "id": 45025,
        "applicationDocumentDetailsList": [
            {
                "id": 30173,
                "activeStatus": "A",
                "modifiedBy": "shine_user",
                "modifiedDate": "2026-03-15T17:22:59.467",
                "application": 45025,
                "documentType": 54,
                "submittedDate": "2026-03-15",
                "filePath": "shine_user/2026-03-15/Reformation of Audit Committee_Shine_1773574663063.pdf",
                "encryptedId": "3f60c84eab311be826f736b584611b2c90886cd585a77d8c60ab40bed40c4397f3fa4582f7744b6e51e544813d642b118136ba7edf0f19f0faebab950ab1a850",
                "fileUrl": "https://www.nepalstock.com.np/api/nots/security/fetchFiles?fileLocation=shine_user/2026-03-15/Reformation%20of%20Audit%20Committee_Shine_1773574663063.pdf"
            }
        ],
        "newsHeadline": "Reformation of Audit Committee _Shine [SHINE] ",
        "newsBody": "<p>Reformation of Audit Committee _Shine</p>",
        "addedDate": "2026-03-15T17:22:59.463",
        "newsSource": "BOD",
        "modifiedDate": "2026-03-16T10:08:38.527",
        "approvedDate": null,
        "symbol": "SHINE"
    },
    {
        "id": 45024,
        "applicationDocumentDetailsList": [
            {
                "id": 30172,
                "activeStatus": "A",
                "modifiedBy": "shine_user",
                "modifiedDate": "2026-03-15T17:20:32.53",
                "application": 45024,
                "documentType": 54,
                "submittedDate": "2026-03-15",
                "filePath": "shine_user/2026-03-15/Appointment of Independent Director_Shine_1773574501446.pdf",
                "encryptedId": "d09c9cf141a4865324bd43c1dfaa3a15add591dca6bd1008f743b534973358e35b417a7aa46cf263f3d8dddfdb67d419c5d096e22098a0c9524dc2669fc9972b",
                "fileUrl": "https://www.nepalstock.com.np/api/nots/security/fetchFiles?fileLocation=shine_user/2026-03-15/Appointment%20of%20Independent%20Director_Shine_1773574501446.pdf"
            }
        ],
        "newsHeadline": "Appointment of Independent Director_Shine [SHINE] ",
        "newsBody": "<p>Appointment of Independent Director_Shine</p>",
        "addedDate": "2026-03-15T17:20:32.527",
        "newsSource": "BOD ",
        "modifiedDate": "2026-03-16T10:08:18.367",
        "approvedDate": null,
        "symbol": "SHINE"
    },
    {
        "id": 45022,
        "applicationDocumentDetailsList": [
            {
                "id": 30171,
                "activeStatus": "A",
                "modifiedBy": "mkjc_user",
                "modifiedDate": "2026-03-15T16:54:44.797",
                "application": 45022,
                "documentType": 54,
                "submittedDate": "2026-03-15",
                "filePath": "mkjc_user/2026-03-15/Appointment of Chairman_1773572808221.pdf",
                "encryptedId": "23aa75eea35615a6d18601856003bfb0c741b0cc0a2f657953d0970217ed92fdc679432c7017474c229211f2376bec956297fef292f21349f4a2af24b50659ee",
                "fileUrl": "https://www.nepalstock.com.np/api/nots/security/fetchFiles?fileLocation=mkjc_user/2026-03-15/Appointment%20of%20Chairman_1773572808221.pdf"
            }
        ],
        "newsHeadline": "Appointment of Chairman [MKJC] ",
        "newsBody": "<p>\u0915\u092e\u094d\u092a\u0928\u0940\u0915\u094b \u0930\u093f\u0915\u094d\u0924 \u0938\u0902\u091a\u093e\u0932\u0915 \u0905\u0927\u094d\u092f\u0915\u094d\u0937 \u092a\u0926\u092e\u093e \u0928\u092f\u093e\u0901 \u0938\u0902\u091a\u093e\u0932\u0915 \u0905\u0927\u094d\u092f\u0915\u094d\u0937 \u0928\u093f\u092f\u0941\u0915\u094d\u0924\u093f \u0917\u0930\u093f\u090f\u0915\u094b \u092c\u093e\u0930\u0947 \u0964</p>",
        "addedDate": "2026-03-15T16:54:44.797",
        "newsSource": "Mailung Khola Jal Vidhyut Company Limited",
        "modifiedDate": "2026-03-15T17:06:14.477",
        "approvedDate": null,
        "symbol": "MKJC"
    },
    {
        "id": 45009,
        "applicationDocumentDetailsList": [
            {
                "id": 30160,
                "activeStatus": "A",
                "modifiedBy": "dolti_user",
                "modifiedDate": "2026-03-15T12:50:39.977",
                "application": 45009,
                "documentType": 54,
                "submittedDate": "2026-03-15",
                "filePath": "Dolti_Power_Company_Limited/Company News/2026-03-15/Dolti Lock-in2026-03-15_095209_1773558002598.pdf",
                "encryptedId": "99a5fa0da91f9fbdc115cd6336a983efbc9da3522499fd39869cb0ea6dc1e6107f145ebd562b5fd6d12f12de41cfd16a99f624ee11ac62e1186810091222fee5",
                "fileUrl": "https://www.nepalstock.com.np/api/nots/security/fetchFiles?fileLocation=Dolti_Power_Company_Limited/Company%20News/2026-03-15/Dolti%20Lock-in2026-03-15_095209_1773558002598.pdf"
            }
        ],
        "newsHeadline": "Lockin Period END [DOLTI] ",
        "newsBody": "",
        "addedDate": "2026-03-15T12:50:39.973",
        "newsSource": "Dolti Power Ltd has announced to release lock in period of shares through Rajdhani News paper as on 2082.12.02",
        "modifiedDate": "2026-03-15T13:47:29.153",
        "approvedDate": null,
        "symbol": "DOLTI"
    },
    {
        "id": 45007,
        "applicationDocumentDetailsList": [
            {
                "id": 30158,
                "activeStatus": "A",
                "modifiedBy": "balephi_user",
                "modifiedDate": "2026-03-15T10:43:50.673",
                "application": 45007,
                "documentType": 54,
                "submittedDate": "2026-03-15",
                "filePath": "Balephi_Hydropower_Limited/Company News/2026-03-15/bhul sachaiyeko_1773550681339.pdf",
                "encryptedId": "06d98bfcbda19a1362b4ca9a37f718d9d5569e89d88ce54d0cd67d54fd56753147e6b3f8f0846ff2e74fb346a6b4bb369635521d0eb58f9b0297d816d968d517",
                "fileUrl": "https://www.nepalstock.com.np/api/nots/security/fetchFiles?fileLocation=Balephi_Hydropower_Limited/Company%20News/2026-03-15/bhul%20sachaiyeko_1773550681339.pdf"
            }
        ],
        "newsHeadline": "Correction of Typing Error [BHL] ",
        "newsBody": "",
        "addedDate": "2026-03-15T10:43:50.667",
        "newsSource": "Correction of Typing Error",
        "modifiedDate": "2026-03-15T10:57:57.507",
        "approvedDate": null,
        "symbol": "BHL"
    },
    {
        "id": 45006,
        "applicationDocumentDetailsList": [
            {
                "id": 30157,
                "activeStatus": "A",
                "modifiedBy": "jslbb_user",
                "modifiedDate": "2026-03-15T08:57:09.347",
                "application": 45006,
                "documentType": 54,
                "submittedDate": "2026-03-15",
                "filePath": "jslbb_user/2026-03-15/AGM Completion _Auditor Appointment_1773544320239.pdf",
                "encryptedId": "b5f4661d53b4103bf9c1b37bde0991d15cf39126862d1904d62fa6f4fbfcaf75aab55ec6db11b1af5dfa4a85e202cb4ab78fb5274a737acd6d2088cbcda0b831",
                "fileUrl": "https://www.nepalstock.com.np/api/nots/security/fetchFiles?fileLocation=jslbb_user/2026-03-15/AGM%20Completion%20_Auditor%20Appointment_1773544320239.pdf"
            }
        ],
        "newsHeadline": "AGM Completion & Auditor Appointment [JSLBB] ",
        "newsBody": "Annual General Meeting of JSLBB\nFiscal Year: 2081-2082\nAGM Type: AGM\nAGM Date: 3/14/2026\nAGM No: 15\nBook Close Date: 2/24/2026",
        "addedDate": "2026-03-15T08:57:09.333",
        "newsSource": "JSLBSL",
        "modifiedDate": "2026-03-15T10:13:30.23",
        "approvedDate": null,
        "symbol": "JSLBB"
    },
    {
        "id": 45005,
        "applicationDocumentDetailsList": [
            {
                "id": 30156,
                "activeStatus": "A",
                "modifiedBy": "rhgcl_user",
                "modifiedDate": "2026-03-13T18:00:05.517",
                "application": 45005,
                "documentType": 54,
                "submittedDate": "2026-03-13",
                "filePath": "Rapti_Hydro_and_General_Construction_Limited/Company News/2026-03-13/Letter_1773404069608.pdf",
                "encryptedId": "4a797a9dff8bb51a90437b954f5b7b3b47225f0f41692f3d96ad3150cf9d9af8555385c107c7c357300f4cc6688c8385e47d095f81b002259f59b1aec3f8134e",
                "fileUrl": "https://www.nepalstock.com.np/api/nots/security/fetchFiles?fileLocation=Rapti_Hydro_and_General_Construction_Limited/Company%20News/2026-03-13/Letter_1773404069608.pdf"
            }
        ],
        "newsHeadline": "Appointment of Issue Manager [RHGCL] ",
        "newsBody": "<p>Appointment of Issue Manager</p>",
        "addedDate": "2026-03-13T18:00:05.517",
        "newsSource": "Appointment of Issue Manager",
        "modifiedDate": "2026-03-15T10:12:58.513",
        "approvedDate": null,
        "symbol": "RHGCL"
    },
    {
        "id": 45003,
        "applicationDocumentDetailsList": [
            {
                "id": 30154,
                "activeStatus": "A",
                "modifiedBy": "sgic_user",
                "modifiedDate": "2026-03-13T16:17:21.203",
                "application": 45003,
                "documentType": 54,
                "submittedDate": "2026-03-13",
                "filePath": "Sanima_General_Insurance_Ltd/Company News/2026-03-13/Nepse_1773397928225.pdf",
                "encryptedId": "7d3b0091f44ea8a0a8b2d58eb6aeeae1ed04e5c1b8482d6789258d058db3fc754e78b05e808ea073317f24aa491c6f4007dd49f7aa2bfc94e8f175fef06c5aad",
                "fileUrl": "https://www.nepalstock.com.np/api/nots/security/fetchFiles?fileLocation=Sanima_General_Insurance_Ltd/Company%20News/2026-03-13/Nepse_1773397928225.pdf"
            }
        ],
        "newsHeadline": "Dividend Declaration [SGIC] ",
        "newsBody": "Dividend Declaration of SGIC\nFiscal Year: 2081-2082\nCash Dividend: 0.2632%\nBonus Shares: 5%",
        "addedDate": "2026-03-13T16:17:21.197",
        "newsSource": "Letter",
        "modifiedDate": "2026-03-15T10:12:10.053",
        "approvedDate": null,
        "symbol": "SGIC"
    },
    {
        "id": 44988,
        "applicationDocumentDetailsList": [
            {
                "id": 30147,
                "activeStatus": "A",
                "modifiedBy": "jbbl_user",
                "modifiedDate": "2026-03-12T18:36:37.3",
                "application": 44988,
                "documentType": 54,
                "submittedDate": "2026-03-12",
                "filePath": "jbbl_user/2026-03-12/After AGM Appointment of Statutory Auditor_1773319856411.pdf",
                "encryptedId": "9bbcf5ec8598f843f3c680c64ea9601623ff24dc13edbe628fb50d81ff205359d78c33d3bbb0eb97da028f827f8be96d4b136b0065677b993927d071ca1d8fe2",
                "fileUrl": "https://www.nepalstock.com.np/api/nots/security/fetchFiles?fileLocation=jbbl_user/2026-03-12/After%20AGM%20Appointment%20of%20Statutory%20Auditor_1773319856411.pdf"
            }
        ],
        "newsHeadline": "AGM Completion & Appointment of Statutory Auditor. [JBBL] ",
        "newsBody": "",
        "addedDate": "2026-03-12T18:36:37.297",
        "newsSource": "AGM",
        "modifiedDate": "2026-03-13T09:34:45.693",
        "approvedDate": null,
        "symbol": "JBBL"
    },
    {
        "id": 44987,
        "applicationDocumentDetailsList": [
            {
                "id": 30146,
                "activeStatus": "A",
                "modifiedBy": "shpc_user",
                "modifiedDate": "2026-03-12T17:12:37.043",
                "application": 44987,
                "documentType": 54,
                "submittedDate": "2026-03-12",
                "filePath": "shpc_user/2026-03-12/Book Close Notice_1773314754513.pdf",
                "encryptedId": "e1322fb6dc9487199d1af15b2f5765e0ba2d84151458b06f803293e54431a753265f89ec2759915eae4da7ba391cd40b1411e062b9fcc4fc970d59e6fdf4b635",
                "fileUrl": "https://www.nepalstock.com.np/api/nots/security/fetchFiles?fileLocation=shpc_user/2026-03-12/Book%20Close%20Notice_1773314754513.pdf"
            }
        ],
        "newsHeadline": "14th AGM declaration and Book Closure date [SHPC] ",
        "newsBody": "Annual General Meeting of SHPC\nFiscal Year: 2081-2082\nAGM Type: AGM\nAGM Date: 4/12/2026\nAGM No: 14\nBook Close Date: 3/26/2026",
        "addedDate": "2026-03-12T17:12:37.037",
        "newsSource": "BOD meeting held on 2082.11.28 at 3:30 Pm onwards",
        "modifiedDate": "2026-03-13T09:34:28.45",
        "approvedDate": null,
        "symbol": "SHPC"
    },
    {
        "id": 44969,
        "applicationDocumentDetailsList": [
            {
                "id": 30133,
                "activeStatus": "A",
                "modifiedBy": "sypnl_uesr",
                "modifiedDate": "2026-03-12T10:44:25.77",
                "application": 44969,
                "documentType": 54,
                "submittedDate": "2026-03-12",
                "filePath": "SY_Panel_Nepal_Limited/Company News/2026-03-12/information_1773291556018.pdf",
                "encryptedId": "88742ad4a5cf4afe958bde7895fbe54b37a1369a2647ba4862e6540641f44cdc47a0f1641a3dc99a563826d19fce7235b1195741685503a2ea5d3420dd800b15",
                "fileUrl": "https://www.nepalstock.com.np/api/nots/security/fetchFiles?fileLocation=SY_Panel_Nepal_Limited/Company%20News/2026-03-12/information_1773291556018.pdf"
            }
        ],
        "newsHeadline": "MD change [SYPNL] ",
        "newsBody": "",
        "addedDate": "2026-03-12T10:44:25.767",
        "newsSource": "Company's BOD meeting minute",
        "modifiedDate": "2026-03-12T10:45:15.893",
        "approvedDate": null,
        "symbol": "SYPNL"
    },
    {
        "id": 44967,
        "applicationDocumentDetailsList": [
            {
                "id": 30130,
                "activeStatus": "A",
                "modifiedBy": "hppl_user",
                "modifiedDate": "2026-03-12T10:28:57.847",
                "application": 44967,
                "documentType": 54,
                "submittedDate": "2026-03-12",
                "filePath": "hppl_user/2026-03-12/book close notice_hppl_1773290605757.pdf",
                "encryptedId": "0438d12aaabc6e994e2d04c0a2cc8bfc764f72ed0e94089a0c1e21c0a32e9ac7f3bbea196e54c8e4e023ebc91f712d4bca3011128228036a6eef8c4660009ccb",
                "fileUrl": "https://www.nepalstock.com.np/api/nots/security/fetchFiles?fileLocation=hppl_user/2026-03-12/book%20close%20notice_hppl_1773290605757.pdf"
            }
        ],
        "newsHeadline": "Book Close [HPPL] ",
        "newsBody": "Book Close of HPPL\nBook Close Date : 3/24/2026",
        "addedDate": "2026-03-12T10:28:57.843",
        "newsSource": "Board Meeting of 2082/11/28",
        "modifiedDate": "2026-03-12T10:31:27.387",
        "approvedDate": null,
        "symbol": "HPPL"
    },
    {
        "id": 44964,
        "applicationDocumentDetailsList": [
            {
                "id": 30127,
                "activeStatus": "A",
                "modifiedBy": "mkcl_user",
                "modifiedDate": "2026-03-12T10:11:38.5",
                "application": 44964,
                "documentType": 54,
                "submittedDate": "2026-03-12",
                "filePath": "Muktinath_Krishi_Company_Limited/Company News/2026-03-12/MKCL Company Secretary Appointment Lette_1773289549854.pdf",
                "encryptedId": "805505bc1ae190f3a3244fdf5a3b2e990fed843b0d8f4cf3f522cc64cb2f1748e9e81a78dffa6091e9cc2df765e3192e01f15b08509940e0acdcb2fdbbbf880e",
                "fileUrl": "https://www.nepalstock.com.np/api/nots/security/fetchFiles?fileLocation=Muktinath_Krishi_Company_Limited/Company%20News/2026-03-12/MKCL%20Company%20Secretary%20Appointment%20Lette_1773289549854.pdf"
            }
        ],
        "newsHeadline": "Mrs. Deepanjali Khakurel appointed as company secretary [MKCL] ",
        "newsBody": "<p>MKCL 104th BoD meeting held on 2082.11.27 appointed Mrs. Deepanjali Khakurel as a Company Secretary.</p>",
        "addedDate": "2026-03-12T10:11:38.493",
        "newsSource": "104th BoD meeting decision regarding appointment of Company Secretary",
        "modifiedDate": "2026-03-12T10:12:49.917",
        "approvedDate": null,
        "symbol": "MKCL"
    },
    {
        "id": 44956,
        "applicationDocumentDetailsList": [
            {
                "id": 30116,
                "activeStatus": "A",
                "modifiedBy": "rlfl_user",
                "modifiedDate": "2026-03-11T15:59:36.197",
                "application": 44956,
                "documentType": 54,
                "submittedDate": "2026-03-11",
                "filePath": "rlfl_user/2026-03-11/Ishwori sir chairman_1773224055917.pdf",
                "encryptedId": "2b2377775910d0b44191f955ddf25a90a02b4b68da834475f00e1b0393b7273b1a212cbbe2cdccfd12370f3ece324f48e9e4bf73ff7b04e13e7a4f533ef52853",
                "fileUrl": "https://www.nepalstock.com.np/api/nots/security/fetchFiles?fileLocation=rlfl_user/2026-03-11/Ishwori%20sir%20chairman_1773224055917.pdf"
            }
        ],
        "newsHeadline": "\u0938\u0902\u091a\u093e\u0932\u0915 \u0938\u092e\u093f\u0924\u093f\u0915\u094b \u0905\u0927\u094d\u092f\u0915\u094d\u0937 \u0928\u093f\u092f\u0941\u0915\u094d\u0924\u0940 \u0938\u092e\u094d\u092c\u0928\u094d\u0927\u092e\u093e \u0964  [RLFL] ",
        "newsBody": "<p>\u092f\u0938 \u0938\u0902\u0938\u094d\u0925\u093e\u0915\u094b\u0947 \u092e\u093f\u0924\u093f \u0968\u0966\u096e\u0968/\u0967\u0967/\u0968\u096d \u0917\u0924\u0947 \u0926\u093f\u0928\u0915\u094b \u0969\u0903\u0966\u0966 \u092c\u091c\u0947 \u092c\u0938\u0947\u0915\u094b \u0938\u0902\u091a\u093e\u0932\u0915 \u0938\u092e\u093f\u0924\u093f\u0915\u094b \u0969\u096c\u0969 \u0914 \u092c\u0948\u0920\u0915\u0932\u0947 \u0938\u0902\u091a\u093e\u0932\u0915 \u0936\u094d\u0930\u0940 \u0908\u0936\u094d\u0935\u0930\u0940 \u092a\u094d\u0930\u0938\u093e\u0926 \u0928\u094d\u092f\u094c\u092a\u093e\u0928\u0947\u0932\u093e\u0908 \u0938\u0902\u091a\u093e\u0932\u0915 \u0938\u092e\u093f\u0924\u093f\u0915\u094b \u0905\u0927\u094d\u092f\u0915\u094d\u0937 \u0928\u093f\u092f\u0941\u0915\u094d\u0924\u0940 \u0917\u0930\u0947\u0915\u094b \u0935\u094d\u092f\u0939\u094b\u0930\u093e \u091c\u093e\u0928\u0915\u093e\u0930\u0940\u0915\u094b \u0932\u093e\u0917\u093f \u0905\u0928\u0941\u0930\u094b\u0927 \u091b \u0964</p>",
        "addedDate": "2026-03-11T15:59:36.193",
        "newsSource": "RFL",
        "modifiedDate": "2026-03-11T16:02:44.237",
        "approvedDate": null,
        "symbol": "RLFL"
    },
    {
        "id": 44947,
        "applicationDocumentDetailsList": [
            {
                "id": 30109,
                "activeStatus": "A",
                "modifiedBy": "bedc_user",
                "modifiedDate": "2026-03-11T11:01:57.44",
                "application": 44947,
                "documentType": 54,
                "submittedDate": "2026-03-11",
                "filePath": "Bhugol_Energy_Development_Company_Limited/Company News/2026-03-11/Bhugol _1773205866527.pdf",
                "encryptedId": "39ef4188cb1ac3b9d560affce09c800ea44594e0b5f85978183affd137dbd6ef0c4f9bba04a85a36193515be60232f3c6259d8f90f2e8f90f4125be79bc87c16",
                "fileUrl": "https://www.nepalstock.com.np/api/nots/security/fetchFiles?fileLocation=Bhugol_Energy_Development_Company_Limited/Company%20News/2026-03-11/Bhugol%20_1773205866527.pdf"
            }
        ],
        "newsHeadline": "Lock-in period end (BEDC) [BEDC] ",
        "newsBody": "<p>Notis published on Rajdhani Newspaper .</p>",
        "addedDate": "2026-03-11T11:01:57.433",
        "newsSource": "Lock-in period end (BEDC) ",
        "modifiedDate": "2026-03-11T11:09:04.723",
        "approvedDate": null,
        "symbol": "BEDC"
    },
    {
        "id": 44938,
        "applicationDocumentDetailsList": [
            {
                "id": 30094,
                "activeStatus": "A",
                "modifiedBy": "ghl_user",
                "modifiedDate": "2026-03-10T10:39:59.507",
                "application": 44938,
                "documentType": 54,
                "submittedDate": "2026-03-10",
                "filePath": "Ghalemdi_Hydro_Limited/Company News/2026-03-10/IMG_0001_1773118467674.pdf",
                "encryptedId": "ff37004e07e1dae57f146b4c134be97f5ad0414bbad886d03bcb8b962e3fea174b34941c696d019ae602a2caaad728cefc9831223ff628a4561b1a8dc682815c",
                "fileUrl": "https://www.nepalstock.com.np/api/nots/security/fetchFiles?fileLocation=Ghalemdi_Hydro_Limited/Company%20News/2026-03-10/IMG_0001_1773118467674.pdf"
            }
        ],
        "newsHeadline": "Company Secretary Resignation and Appointment [GHL] ",
        "newsBody": "",
        "addedDate": "2026-03-10T10:39:59.483",
        "newsSource": "Company Secretary Resignation and Appointment",
        "modifiedDate": "2026-03-10T10:40:52.903",
        "approvedDate": null,
        "symbol": "GHL"
    },
    {
        "id": 44936,
        "applicationDocumentDetailsList": [
            {
                "id": 30091,
                "activeStatus": "A",
                "modifiedBy": "makar_user",
                "modifiedDate": "2026-03-09T10:21:48.55",
                "application": 44936,
                "documentType": 54,
                "submittedDate": "2026-03-09",
                "filePath": "Makar_Jitumaya_Suri_Hydropower_Limited/Company News/2026-03-09/Letter OF Locking release_1773030929603.pdf",
                "encryptedId": "1ca55173984ae9f4e6d2aae5ab8cbd414594a55eff6b29bf8f3dbbbf88ec41adb4eecb4aa041413e5c2ca7020e5c08ae971bcc7ff87d208868aedee0579c6d44",
                "fileUrl": "https://www.nepalstock.com.np/api/nots/security/fetchFiles?fileLocation=Makar_Jitumaya_Suri_Hydropower_Limited/Company%20News/2026-03-09/Letter%20OF%20Locking%20release_1773030929603.pdf"
            },
            {
                "id": 30089,
                "activeStatus": "A",
                "modifiedBy": "makar_user",
                "modifiedDate": "2026-03-09T10:21:48.55",
                "application": 44936,
                "documentType": 54,
                "submittedDate": "2026-03-09",
                "filePath": "Makar_Jitumaya_Suri_Hydropower_Limited/Company News/2026-03-09/Pages from Locking Release notic Prakshepa_25 fagun_1773030948471.pdf",
                "encryptedId": "3bfa72f724a58c183f20f3fe2d0a6693cd98b9ba9e837dda5aea13e4069b3176ea163dd84390d2fbb9182e01970528d5f9a03257751f55032473d67804ac0b63",
                "fileUrl": "https://www.nepalstock.com.np/api/nots/security/fetchFiles?fileLocation=Makar_Jitumaya_Suri_Hydropower_Limited/Company%20News/2026-03-09/Pages%20from%20Locking%20Release%20notic%20Prakshepa_25%20fagun_1773030948471.pdf"
            },
            {
                "id": 30090,
                "activeStatus": "A",
                "modifiedBy": "makar_user",
                "modifiedDate": "2026-03-09T10:21:48.55",
                "application": 44936,
                "documentType": 54,
                "submittedDate": "2026-03-09",
                "filePath": "Makar_Jitumaya_Suri_Hydropower_Limited/Company News/2026-03-09/Makar Jitu Lockin Notice_3x20cc_25_gate_1773030979870.pdf",
                "encryptedId": "82b224504d8b96579cbf4e5c7a7f1def275495e23b642c0b2c5387d1b400ae91c7eb5455e08db948d729948b8f017a5b7b6328e928a9b99e5a1e27a136a3412f",
                "fileUrl": "https://www.nepalstock.com.np/api/nots/security/fetchFiles?fileLocation=Makar_Jitumaya_Suri_Hydropower_Limited/Company%20News/2026-03-09/Makar%20Jitu%20Lockin%20Notice_3x20cc_25_gate_1773030979870.pdf"
            }
        ],
        "newsHeadline": "Open Lock In Period  [MAKAR] ",
        "newsBody": "",
        "addedDate": "2026-03-09T10:21:48.543",
        "newsSource": "https://prakshepandaily.com/2026/03/09/59386/",
        "modifiedDate": "2026-03-09T10:36:16.023",
        "approvedDate": null,
        "symbol": "MAKAR"
    },
    {
        "id": 44933,
        "applicationDocumentDetailsList": [
            {
                "id": 30086,
                "activeStatus": "A",
                "modifiedBy": "mhl_user",
                "modifiedDate": "2026-03-08T14:52:01.743",
                "application": 44933,
                "documentType": 54,
                "submittedDate": "2026-03-08",
                "filePath": "Mandakini_Hydropower_Limited/Company News/2026-03-08/letter_1772960784277.pdf",
                "encryptedId": "45086dcaae8c4cc14bce29696b64b3023ce0f66eaebcbf78faafae51ac3dbd1513aa51ad327a7d71dc710d474fe517627b0419ed000905d26ac5fa16563fe95f",
                "fileUrl": "https://www.nepalstock.com.np/api/nots/security/fetchFiles?fileLocation=Mandakini_Hydropower_Limited/Company%20News/2026-03-08/letter_1772960784277.pdf"
            }
        ],
        "newsHeadline": "Appointment of Managing Director/CEO [MHL] ",
        "newsBody": "",
        "addedDate": "2026-03-08T14:52:01.737",
        "newsSource": "BOD",
        "modifiedDate": "2026-03-09T09:00:08.327",
        "approvedDate": null,
        "symbol": "MHL"
    },
    {
        "id": 44931,
        "applicationDocumentDetailsList": [
            {
                "id": 30084,
                "activeStatus": "A",
                "modifiedBy": "mhl_user",
                "modifiedDate": "2026-03-03T16:52:46.69",
                "application": 44931,
                "documentType": 54,
                "submittedDate": "2026-03-03",
                "filePath": "Mandakini_Hydropower_Limited/Company News/2026-03-03/mhl letter_1772535941986.pdf",
                "encryptedId": "cecfcf4fb896dcb9580aaa595c7faac46089f164ac4b5591747c5c6986f813712a77dbf402abcc61f27585437d9b5518d13981b3fd3c9fc0968f9488f7606843",
                "fileUrl": "https://www.nepalstock.com.np/api/nots/security/fetchFiles?fileLocation=Mandakini_Hydropower_Limited/Company%20News/2026-03-03/mhl%20letter_1772535941986.pdf"
            }
        ],
        "newsHeadline": "Resignation of Chairman [MHL] ",
        "newsBody": "",
        "addedDate": "2026-03-03T16:52:46.687",
        "newsSource": "BOD",
        "modifiedDate": "2026-03-09T08:59:13.043",
        "approvedDate": null,
        "symbol": "MHL"
    },
    {
        "id": 44928,
        "applicationDocumentDetailsList": [
            {
                "id": 30083,
                "activeStatus": "A",
                "modifiedBy": "alicl_user",
                "modifiedDate": "2026-03-03T15:37:36.857",
                "application": 44928,
                "documentType": 54,
                "submittedDate": "2026-03-03",
                "filePath": "alicl_user/2026-03-03/ALICL 18th AGM Minute_1772531464950.pdf",
                "encryptedId": "45f0f5ecc539614a02e11d5c6bd49fafe448070f02a19ffe81d1acc232fe6bee8fa3c58b59094712da46fb6299b2a35a58a250a530b9544260f290ff1cc1128b",
                "fileUrl": "https://www.nepalstock.com.np/api/nots/security/fetchFiles?fileLocation=alicl_user/2026-03-03/ALICL%2018th%20AGM%20Minute_1772531464950.pdf"
            }
        ],
        "newsHeadline": "18th AGM Minute [ALICL] ",
        "newsBody": "",
        "addedDate": "2026-03-03T15:37:36.853",
        "newsSource": "Asian Life Insurance Company Ltd.",
        "modifiedDate": "2026-03-03T15:40:16.557",
        "approvedDate": null,
        "symbol": "ALICL"
    },
    {
        "id": 44919,
        "applicationDocumentDetailsList": [
            {
                "id": 30073,
                "activeStatus": "A",
                "modifiedBy": "hli_user",
                "modifiedDate": "2026-03-03T10:29:31.777",
                "application": 44919,
                "documentType": 54,
                "submittedDate": "2026-03-03",
                "filePath": "hli_user/2026-03-03/Minute Letter_1772513008656.pdf",
                "encryptedId": "c398d3cfe067d50c28f874621604d4bbf5a021855fde4bb0088ee7a9f3638f560106d83a5e106260e062c7d91f1deb7f2528a63c052f8e45dd07d07d9463b30a",
                "fileUrl": "https://www.nepalstock.com.np/api/nots/security/fetchFiles?fileLocation=hli_user/2026-03-03/Minute%20Letter_1772513008656.pdf"
            },
            {
                "id": 30074,
                "activeStatus": "A",
                "modifiedBy": "hli_user",
                "modifiedDate": "2026-03-03T10:29:31.78",
                "application": 44919,
                "documentType": 54,
                "submittedDate": "2026-03-03",
                "filePath": "hli_user/2026-03-03/19th AGM Minute_1772513018695.pdf",
                "encryptedId": "9fb879af1af6a5ff99d7bc9eb59360a867507fffea4b30e46e4c82c42297f0ddd14a186cdce4cdb7980255b7de64a47f0a8a8790cb136c45a66df7cd46ef3e25",
                "fileUrl": "https://www.nepalstock.com.np/api/nots/security/fetchFiles?fileLocation=hli_user/2026-03-03/19th%20AGM%20Minute_1772513018695.pdf"
            }
        ],
        "newsHeadline": "19th AGM Minute [HLI] ",
        "newsBody": "<p>19th AGM Minute</p>",
        "addedDate": "2026-03-03T10:29:31.773",
        "newsSource": "19th Annual General Meetings",
        "modifiedDate": "2026-03-03T10:30:52.43",
        "approvedDate": null,
        "symbol": "HLI"
    },
    {
        "id": 44918,
        "applicationDocumentDetailsList": [
            {
                "id": 30072,
                "activeStatus": "A",
                "modifiedBy": "gmfbs_user",
                "modifiedDate": "2026-03-03T10:28:32.453",
                "application": 44918,
                "documentType": 54,
                "submittedDate": "2026-03-03",
                "filePath": "Ganapati_Microfinance_Bittiya_Sanstha_Ltd/Company News/2026-03-03/AGM Notice In News_1772512991621.jpg",
                "encryptedId": "9fb4062890133ca61954b7ff4ad9b39092f84068ec0b67e1433a796688e1ef9b17828473f6fefbb1d7ff1298fa9ef714bb95ad3c2b8bfa3c1b39f309b81628d2",
                "fileUrl": "https://www.nepalstock.com.np/api/nots/security/fetchFiles?fileLocation=Ganapati_Microfinance_Bittiya_Sanstha_Ltd/Company%20News/2026-03-03/AGM%20Notice%20In%20News_1772512991621.jpg"
            },
            {
                "id": 30070,
                "activeStatus": "A",
                "modifiedBy": "gmfbs_user",
                "modifiedDate": "2026-03-03T10:28:32.453",
                "application": 44918,
                "documentType": 54,
                "submittedDate": "2026-03-03",
                "filePath": "Ganapati_Microfinance_Bittiya_Sanstha_Ltd/Company News/2026-03-03/AGM Notice Letter_1772512972243.pdf",
                "encryptedId": "b8ff20023cae0a84f16835b9692979d0a78ea7d33ffdd857773d62aba23ceb41703d0b54c124dd8301f6f61c61f2052acf4101b2112b453dc2baeb899ced9aaf",
                "fileUrl": "https://www.nepalstock.com.np/api/nots/security/fetchFiles?fileLocation=Ganapati_Microfinance_Bittiya_Sanstha_Ltd/Company%20News/2026-03-03/AGM%20Notice%20Letter_1772512972243.pdf"
            },
            {
                "id": 30071,
                "activeStatus": "A",
                "modifiedBy": "gmfbs_user",
                "modifiedDate": "2026-03-03T10:28:32.453",
                "application": 44918,
                "documentType": 54,
                "submittedDate": "2026-03-03",
                "filePath": "Ganapati_Microfinance_Bittiya_Sanstha_Ltd/Company News/2026-03-03/Ganapati AGM Notice 3x34_1772512980668.pdf",
                "encryptedId": "09628e25c125491cef62bb8b31d96dc5f9e76315af7ff852514ec1bf36091f338517daeb9c57f5800c3bd0944e963142e7ea991a2e463ca44dd7cbe3fe5f1f47",
                "fileUrl": "https://www.nepalstock.com.np/api/nots/security/fetchFiles?fileLocation=Ganapati_Microfinance_Bittiya_Sanstha_Ltd/Company%20News/2026-03-03/Ganapati%20AGM%20Notice%203x34_1772512980668.pdf"
            }
        ],
        "newsHeadline": "9th AGM Notice & Book Closer Date of GMFBS [GMFBS] ",
        "newsBody": "Book Close of GMFBS\nBook Close Date : 12/3/2082",
        "addedDate": "2026-03-03T10:28:32.447",
        "newsSource": "Board Meeting",
        "modifiedDate": "2026-03-03T10:30:04.323",
        "approvedDate": null,
        "symbol": "GMFBS"
    },
    {
        "id": 44916,
        "applicationDocumentDetailsList": [
            {
                "id": 30068,
                "activeStatus": "A",
                "modifiedBy": "gfcl_user",
                "modifiedDate": "2026-03-03T10:03:34.86",
                "application": 44916,
                "documentType": 54,
                "submittedDate": "2026-03-03",
                "filePath": "gfcl_user/2026-03-03/Nepal Stock Exchange Ltd_1772511483345.pdf",
                "encryptedId": "793e11e6e5eb39ed82a56973edd537e1b2be58f6f35acae012a427aff1c27bd0de20abbca953fb556ed2e027e18eee40825a1bf8385210287bddccd1a6cd6c50",
                "fileUrl": "https://www.nepalstock.com.np/api/nots/security/fetchFiles?fileLocation=gfcl_user/2026-03-03/Nepal%20Stock%20Exchange%20Ltd_1772511483345.pdf"
            }
        ],
        "newsHeadline": "Information regarding 31st AGM and Book closer date [GFCL] ",
        "newsBody": "Annual General Meeting of GFCL\nFiscal Year: 2081-2082\nAGM Type: AGM\nAGM Date: 3/24/2026\nAGM No: 31\nBook Close Date: 3/16/2026",
        "addedDate": "2026-03-03T10:03:34.837",
        "newsSource": "Information regarding 31st AGM and Book closer date",
        "modifiedDate": "2026-03-03T10:04:08.947",
        "approvedDate": null,
        "symbol": "GFCL"
    },
    {
        "id": 44915,
        "applicationDocumentDetailsList": [
            {
                "id": 30067,
                "activeStatus": "A",
                "modifiedBy": "corbl_user",
                "modifiedDate": "2026-03-02T15:48:14",
                "application": 44915,
                "documentType": 54,
                "submittedDate": "2026-03-02",
                "filePath": "corbl_user/2026-03-02/18 AGM_1772445786709.pdf",
                "encryptedId": "3deec32f1417bd08e4d69e707476cf547c80be7322d12f78a79f7a4b6f7a536ddabbcb0af5dcde06f7944bb2cbdce567958788dd88c7ddfe672e2c5de4a56e0d",
                "fileUrl": "https://www.nepalstock.com.np/api/nots/security/fetchFiles?fileLocation=corbl_user/2026-03-02/18%20AGM_1772445786709.pdf"
            }
        ],
        "newsHeadline": "AGM Minutes [CORBL] ",
        "newsBody": "",
        "addedDate": "2026-03-02T15:48:13.997",
        "newsSource": "Corporate AGM Minutes",
        "modifiedDate": "2026-03-03T10:04:27.417",
        "approvedDate": null,
        "symbol": "CORBL"
    },
    {
        "id": 44914,
        "applicationDocumentDetailsList": [
            {
                "id": 30066,
                "activeStatus": "A",
                "modifiedBy": "jfl_user",
                "modifiedDate": "2026-03-02T13:51:32.887",
                "application": 44914,
                "documentType": 54,
                "submittedDate": "2026-03-02",
                "filePath": "jfl_user/2026-03-02/Chairman_1772438726093.jpg",
                "encryptedId": "0a81002a338c23132eb562f575d00d36d545856ef639bde797a993aa398b6644745f58253043ff9fe6e33abfe8db8a073c7008d148578f396b71a206bbff9ba8",
                "fileUrl": "https://www.nepalstock.com.np/api/nots/security/fetchFiles?fileLocation=jfl_user/2026-03-02/Chairman_1772438726093.jpg"
            }
        ],
        "newsHeadline": "Nominated of Chairman (JFL). [JFL] ",
        "newsBody": "<p>Nominated of Chairman (JFL).</p>",
        "addedDate": "2026-03-02T13:51:32.883",
        "newsSource": "Janaki Finance Company Limited",
        "modifiedDate": "2026-03-03T10:03:33.893",
        "approvedDate": null,
        "symbol": "JFL"
    },
    {
        "id": 44913,
        "applicationDocumentDetailsList": [
            {
                "id": 30065,
                "activeStatus": "A",
                "modifiedBy": "jfl_user",
                "modifiedDate": "2026-03-02T13:48:57.707",
                "application": 44913,
                "documentType": 54,
                "submittedDate": "2026-03-02",
                "filePath": "jfl_user/2026-03-02/Appointment of CEO_1772438610971.jpg",
                "encryptedId": "d87d40021b38eb4deeeb6ed77d5750bd6f1ef8a5085cda642bbb24dbe9499689c374118c07a5d8072d50d29036922ccfeeb002db6198dd716c067f11cb45170f",
                "fileUrl": "https://www.nepalstock.com.np/api/nots/security/fetchFiles?fileLocation=jfl_user/2026-03-02/Appointment%20of%20CEO_1772438610971.jpg"
            }
        ],
        "newsHeadline": "Appointment of CEO (JFL) [JFL] ",
        "newsBody": "<p>Appointment of CEO (JFL).</p>",
        "addedDate": "2026-03-02T13:48:57.703",
        "newsSource": "Janaki Finance Company Limited",
        "modifiedDate": "2026-03-03T10:03:15.727",
        "approvedDate": null,
        "symbol": "JFL"
    },
    {
        "id": 44912,
        "applicationDocumentDetailsList": [
            {
                "id": 30064,
                "activeStatus": "A",
                "modifiedBy": "corbl_user",
                "modifiedDate": "2026-03-02T13:11:39.59",
                "application": 44912,
                "documentType": 54,
                "submittedDate": "2026-03-02",
                "filePath": "corbl_user/2026-03-02/Corbl Letter_1772436391294.jpeg",
                "encryptedId": "26a9a00d3ca1e390b83e45c42ef918f426aeab55f51329ef02a0b70bb9e6f8186cb0f3b11946d4dfdec7c4ad94c8a900f13c4bf1e36ad444ce3edf07f47e40e2",
                "fileUrl": "https://www.nepalstock.com.np/api/nots/security/fetchFiles?fileLocation=corbl_user/2026-03-02/Corbl%20Letter_1772436391294.jpeg"
            }
        ],
        "newsHeadline": "Appointment for Auditor - Devki Bijay & Corporation [CORBL] ",
        "newsBody": "",
        "addedDate": "2026-03-02T13:11:39.587",
        "newsSource": "Company Letter",
        "modifiedDate": "2026-03-03T10:02:54.013",
        "approvedDate": null,
        "symbol": "CORBL"
    },
    {
        "id": 44909,
        "applicationDocumentDetailsList": [
            {
                "id": 30061,
                "activeStatus": "A",
                "modifiedBy": "corbl_user",
                "modifiedDate": "2026-03-02T11:08:03.347",
                "application": 44909,
                "documentType": 54,
                "submittedDate": "2026-03-02",
                "filePath": "corbl_user/2026-03-02/AGM Minutes_1772428967673.pdf",
                "encryptedId": "120955837592b3b583d2b3c23a521e52af96f3f6d95ca3cc48835ce5687a7b8418762d60855ea952ed33c391cd99bbc2785a2193bc9da425cf82dba330090cad",
                "fileUrl": "https://www.nepalstock.com.np/api/nots/security/fetchFiles?fileLocation=corbl_user/2026-03-02/AGM%20Minutes_1772428967673.pdf"
            }
        ],
        "newsHeadline": "AGM Minutes [CORBL] ",
        "newsBody": "",
        "addedDate": "2026-03-02T11:08:03.343",
        "newsSource": "Corporate AGM Minutes",
        "modifiedDate": "2026-03-03T10:01:59.617",
        "approvedDate": null,
        "symbol": "CORBL"
    },
    {
        "id": 44907,
        "applicationDocumentDetailsList": [
            {
                "id": 30059,
                "activeStatus": "A",
                "modifiedBy": "rlfl_user",
                "modifiedDate": "2026-03-01T18:12:00.563",
                "application": 44907,
                "documentType": 54,
                "submittedDate": "2026-03-01",
                "filePath": "rlfl_user/2026-03-01/susila Adhikari kandel_1772367989985.pdf",
                "encryptedId": "6914aad435947829d11babf90e98edb85e6a8741cec28e774ea71171b6afd37aaabbb6ebbdc3a9507e7598780d5e6fb5dea14be7429a9c9f379a1b79462df4d6",
                "fileUrl": "https://www.nepalstock.com.np/api/nots/security/fetchFiles?fileLocation=rlfl_user/2026-03-01/susila%20Adhikari%20kandel_1772367989985.pdf"
            }
        ],
        "newsHeadline": "\u0938\u0902\u091a\u093e\u0932\u0915 \u0928\u093f\u092f\u0941\u0915\u094d\u0924\u0940 \u0938\u092e\u094d\u092c\u0928\u094d\u0927\u092e\u093e \u0964  [RLFL] ",
        "newsBody": "<p>\u092f\u0938 \u0938\u0902\u0938\u094d\u0925\u093e\u0915\u094b\u0947 \u092e\u093f\u0924\u093f \u0968\u0966\u096e\u0968/\u0967\u0967/\u0967\u096d \u0917\u0924\u0947 \u0926\u093f\u0928\u0915\u094b \u0969\u0903\u0966\u0966 \u092c\u091c\u0947 \u092c\u0938\u0947\u0915\u094b \u0938\u0902\u091a\u093e\u0932\u0915 \u0938\u092e\u093f\u0924\u093f\u0915\u094b \u0969\u096c\u0968 \u0914 \u092c\u0948\u0920\u0915\u0932\u0947 \u0938\u0902\u0938\u094d\u0925\u093e\u092a\u0915 \u0936\u0947\u092f\u0930\u0927\u0928\u0940\u0915\u094b \u0924\u0930\u094d\u092b\u092c\u093e\u091f \u092a\u094d\u0930\u0924\u093f\u0928\u093f\u0927\u093f\u0924\u094d\u0935 \u0939\u0941\u0928\u0947 \u0930\u093f\u0915\u094d\u0924 \u0930\u0939\u0947\u0915\u094b \u0938\u0902\u091a\u093e\u0932\u0915 \u092a\u0926\u092e\u093e \u092c\u093e\u0901\u0915\u0940 \u0905\u0935\u0927\u0940\u0915\u093e \u0932\u093e\u0917\u093f \u0936\u094d\u0930\u0940 \u0938\u0941\u0936\u093f\u0932\u093e \u0905\u0927\u093f\u0915\u093e\u0930\u0940 \u0915\u0921\u0947\u0902\u0932\u0932\u093e\u0908 \u0928\u093f\u092f\u0941\u0915\u094d\u0924\u0940 \u0917\u0930\u0947\u0915\u094b \u0935\u094d\u092f\u0939\u094b\u0930\u093e \u091c\u093e\u0928\u0915\u093e\u0930\u0940\u0915\u094b \u0932\u093e\u0917\u093f \u0905\u0928\u0941\u0930\u094b\u0927 \u091b \u0964</p>",
        "addedDate": "2026-03-01T18:12:00.557",
        "newsSource": "RFL",
        "modifiedDate": "2026-03-03T10:00:56.137",
        "approvedDate": null,
        "symbol": "RLFL"
    },
    {
        "id": 44906,
        "applicationDocumentDetailsList": [
            {
                "id": 30058,
                "activeStatus": "A",
                "modifiedBy": "ili_user",
                "modifiedDate": "2026-03-01T16:56:05.98",
                "application": 44906,
                "documentType": 54,
                "submittedDate": "2026-03-01",
                "filePath": "IME_Life_Insurance_Company_Limited/Company News/2026-03-01/Resignation of Public Director NEPSE_1772363452287.pdf",
                "encryptedId": "0e135df8cdae40f9c02535d8a7ca858a05c488fc5dd49d87d27b91f7ea36d1787501d136c7507eb2bd31595e77458ea390599cef09066c99fdf512ffb9965ddc",
                "fileUrl": "https://www.nepalstock.com.np/api/nots/security/fetchFiles?fileLocation=IME_Life_Insurance_Company_Limited/Company%20News/2026-03-01/Resignation%20of%20Public%20Director%20NEPSE_1772363452287.pdf"
            }
        ],
        "newsHeadline": "Resignation of Board of Director [ILI] ",
        "newsBody": "<p>Dear Sir/Madam,</p><p></p><p>Please do find the information regarding resignation of Board of Director.</p><p>Regards</p><p>Prakash Neupane </p>",
        "addedDate": "2026-03-01T16:56:05.977",
        "newsSource": "Decision of Board ",
        "modifiedDate": "2026-03-03T10:00:36.92",
        "approvedDate": null,
        "symbol": "ILI"
    },
    {
        "id": 44902,
        "applicationDocumentDetailsList": [
            {
                "id": 30056,
                "activeStatus": "A",
                "modifiedBy": "mehl_user",
                "modifiedDate": "2026-03-01T15:13:48.723",
                "application": 44902,
                "documentType": 54,
                "submittedDate": "2026-03-01",
                "filePath": "Manakamana_Engineering_Hydropower_Limited/Company News/2026-03-01/sgm completion letter_1772357240428.pdf",
                "encryptedId": "78bff54997b9699b298ecb389f10e8ac2a1ab4c90cb595f9deb00595a835f60d55cff61126fa5cdeb09dcf7992b176fa2bc2f3817c8b84e147a2a89816319b0e",
                "fileUrl": "https://www.nepalstock.com.np/api/nots/security/fetchFiles?fileLocation=Manakamana_Engineering_Hydropower_Limited/Company%20News/2026-03-01/sgm%20completion%20letter_1772357240428.pdf"
            },
            {
                "id": 30055,
                "activeStatus": "A",
                "modifiedBy": "mehl_user",
                "modifiedDate": "2026-03-01T15:13:48.723",
                "application": 44902,
                "documentType": 54,
                "submittedDate": "2026-03-01",
                "filePath": "Manakamana_Engineering_Hydropower_Limited/Company News/2026-03-01/sgm completion minute_1772357244830.pdf",
                "encryptedId": "ba508515f0c660652fdb98128587e4af23bdb488eb94118eb3b8c606bf5d532e98f3b4a1b0b58fb45e236f39dab4f7273d8b1991ab11768061220e262e0b76b9",
                "fileUrl": "https://www.nepalstock.com.np/api/nots/security/fetchFiles?fileLocation=Manakamana_Engineering_Hydropower_Limited/Company%20News/2026-03-01/sgm%20completion%20minute_1772357244830.pdf"
            }
        ],
        "newsHeadline": "MEHL has successfully completed its SGM. [MEHL] ",
        "newsBody": "<p>MEHL has successfully completed its SGM dated on 17/11/2082  B.S. at Kwality Banquet, Buddhanagar, Kathmandu. </p>",
        "addedDate": "2026-03-01T15:13:48.713",
        "newsSource": "SGM ",
        "modifiedDate": "2026-03-01T15:17:22.347",
        "approvedDate": null,
        "symbol": "MEHL"
    },
    {
        "id": 44898,
        "applicationDocumentDetailsList": [
            {
                "id": 30054,
                "activeStatus": "A",
                "modifiedBy": "sindu_user",
                "modifiedDate": "2026-03-01T10:34:08.907",
                "application": 44898,
                "documentType": 54,
                "submittedDate": "2026-03-01",
                "filePath": "sindu_user/2026-03-01/Re-notice_1772340447517.pdf",
                "encryptedId": "b1e449331525a8e72d8075421634bf4e58d52d3a086fa31e74b10c66defe7ba88f6eabb7925da89c023e5a87a405e71f5e799ff449f57fd9b459237383b502d1",
                "fileUrl": "https://www.nepalstock.com.np/api/nots/security/fetchFiles?fileLocation=sindu_user/2026-03-01/Re-notice_1772340447517.pdf"
            }
        ],
        "newsHeadline": "Information about re-announcement of AGM [SINDU] ",
        "newsBody": "<p><span style=\"color: rgb(85, 85, 85); font-family: &quot;Source Sans Pro&quot;, sans-serif; font-size: 14px; font-style: normal; font-variant-ligatures: normal; font-variant-caps: normal; font-weight: 400; letter-spacing: normal; orphans: 2; text-align: left; text-indent: 0px; text-transform: none; widows: 2; word-spacing: 0px; -webkit-text-stroke-width: 0px; white-space: normal; background-color: rgba(0, 0, 0, 0.05); text-decoration-thickness: initial; text-decoration-style: initial; text-decoration-color: initial; display: inline !important; float: none;\">Information about re-announcement of 16th AGM with published notice in Karobar national daily.</span></p>",
        "addedDate": "2026-03-01T10:34:08.883",
        "newsSource": "BOD meeting",
        "modifiedDate": "2026-03-01T10:42:46.843",
        "approvedDate": null,
        "symbol": "SINDU"
    },
    {
        "id": 44895,
        "applicationDocumentDetailsList": [
            {
                "id": 30051,
                "activeStatus": "A",
                "modifiedBy": "smfbs_user",
                "modifiedDate": "2026-02-27T15:40:43.96",
                "application": 44895,
                "documentType": 54,
                "submittedDate": "2026-02-27",
                "filePath": "Swabhimaan_Laghubitta_Bittiya_Sanstha_Ltd/Company News/2026-02-27/img001_1772186042419.pdf",
                "encryptedId": "0dfaaddb7d941147bd8777b6e19ceb7b4e305c79a14ef51c14b4b129030eb9e6aa98b58c8ff6c923d5faeadd9bb726bf755898466265c0f3c2141f8f1c50228c",
                "fileUrl": "https://www.nepalstock.com.np/api/nots/security/fetchFiles?fileLocation=Swabhimaan_Laghubitta_Bittiya_Sanstha_Ltd/Company%20News/2026-02-27/img001_1772186042419.pdf"
            }
        ],
        "newsHeadline": "Dividend Declaration [SMFBS] ",
        "newsBody": "Dividend Declaration of SMFBS\nFiscal Year: 2081-2082\nCash Dividend: 0.5%\nBonus Shares: 9.5%",
        "addedDate": "2026-02-27T15:40:43.953",
        "newsSource": "Company Secretary",
        "modifiedDate": "2026-03-01T10:00:36.667",
        "approvedDate": null,
        "symbol": "SMFBS"
    },
    {
        "id": 44837,
        "applicationDocumentDetailsList": [
            {
                "id": 29993,
                "activeStatus": "A",
                "modifiedBy": "user_sagar",
                "modifiedDate": "2026-02-22T10:14:46.097",
                "application": 44837,
                "documentType": 54,
                "submittedDate": "2026-02-22",
                "filePath": "Sagar_Distillery_Limited/Company News/2026-02-22/NSP fagun10 sunday epaper pdf-3_1771734582853.pdf",
                "encryptedId": "eb78953229dc6bdaac6294c7485a5b471c0ff2532ec331875bedab6e628f2b11ef0e2827c451cf8995c33a1a1458a9e08456378bbd855e72d0c085920a95ded3",
                "fileUrl": "https://www.nepalstock.com.np/api/nots/security/fetchFiles?fileLocation=Sagar_Distillery_Limited/Company%20News/2026-02-22/NSP%20fagun10%20sunday%20epaper%20pdf-3_1771734582853.pdf"
            },
            {
                "id": 29994,
                "activeStatus": "A",
                "modifiedBy": "user_sagar",
                "modifiedDate": "2026-02-22T10:14:46.097",
                "application": 44837,
                "documentType": 54,
                "submittedDate": "2026-02-22",
                "filePath": "Sagar_Distillery_Limited/Company News/2026-02-22/Nepse_1771734575891.pdf",
                "encryptedId": "4af30b9d4979478b2730367fa91507f8571bcf7ca1f6d68485c238b824988d70d7386442ac67adea682df71dee82c3fcf09331baddfebb6bf0e83a07b864ec7e",
                "fileUrl": "https://www.nepalstock.com.np/api/nots/security/fetchFiles?fileLocation=Sagar_Distillery_Limited/Company%20News/2026-02-22/Nepse_1771734575891.pdf"
            }
        ],
        "newsHeadline": "\u0938\u093e\u092e\u0942\u0939\u093f\u0915 \u0932\u0917\u093e\u0928\u0940 \u0915\u094b\u0937\u0939\u0930\u0941\u0915\u094b \u0932\u093e\u0917\u093f \u091b\u0941\u091f\u094d\u091f\u093e\u0907\u090f\u0915\u094b \u0938\u093e\u0927\u093e\u0930\u0923 \u0936\u0947\u092f\u0930\u0915\u094b \u0932\u0915-\u0908\u0928 \u0905\u0935\u0927\u093f \u0938\u092e\u093e\u092a\u094d\u0924\u0940 \u0938\u092e\u094d\u092c\u0928\u094d\u0927\u0940 \u0938\u0942\u091a\u0928\u093e [SAGAR] ",
        "newsBody": "",
        "addedDate": "2026-02-22T10:14:46.077",
        "newsSource": "Nepal Samacharpatra",
        "modifiedDate": "2026-02-22T10:16:43.137",
        "approvedDate": null,
        "symbol": "SAGAR"
    },
    {
        "id": 44816,
        "applicationDocumentDetailsList": [
            {
                "id": 29974,
                "activeStatus": "A",
                "modifiedBy": "slbsl_user",
                "modifiedDate": "2026-02-17T10:42:52.657",
                "application": 44816,
                "documentType": 54,
                "submittedDate": "2026-02-17",
                "filePath": "Samudayik_Laghubitta_Bittiya_Sanstha_Limited/Company News/2026-02-17/Notice_Lock in period end_1771304122239.jpg",
                "encryptedId": "963d59d6355709e3699349e371840f4462d195096f125d5bfe0f6c8572f9a4690209d6a745dc4998ad810be12ac14693fbf0aaff2b2468cf5d6f2a78f8bd1094",
                "fileUrl": "https://www.nepalstock.com.np/api/nots/security/fetchFiles?fileLocation=Samudayik_Laghubitta_Bittiya_Sanstha_Limited/Company%20News/2026-02-17/Notice_Lock%20in%20period%20end_1771304122239.jpg"
            },
            {
                "id": 29975,
                "activeStatus": "A",
                "modifiedBy": "slbsl_user",
                "modifiedDate": "2026-02-17T10:42:52.657",
                "application": 44816,
                "documentType": 54,
                "submittedDate": "2026-02-17",
                "filePath": "Samudayik_Laghubitta_Bittiya_Sanstha_Limited/Company News/2026-02-17/Information to Nepse_Lock in period_1771304110682.pdf",
                "encryptedId": "32efa875a5e0e77976d842aa7994e3fcdaab7058225c8da93a90b74245b8ea18d1002881080df2671d11d2602e9c32b956ecfde6160ae8e9d0ece7e44c13c847",
                "fileUrl": "https://www.nepalstock.com.np/api/nots/security/fetchFiles?fileLocation=Samudayik_Laghubitta_Bittiya_Sanstha_Limited/Company%20News/2026-02-17/Information%20to%20Nepse_Lock%20in%20period_1771304110682.pdf"
            }
        ],
        "newsHeadline": "Lock in period end [SLBSL] ",
        "newsBody": "<p>Dear Sir,</p><p>Here is attached an information about the end of lock in period of shares investors of BPW Laghubitta Bittiya Sanstha Limited which has been merged with Samudayik Laghubitta Bittiya Sanstha Limited and had started  its integrated transaction as Samudayik since 2080 Falgun 24.</p>",
        "addedDate": "2026-02-17T10:42:52.653",
        "newsSource": "Information about Lock in period end ",
        "modifiedDate": "2026-02-17T10:56:04.087",
        "approvedDate": null,
        "symbol": "SLBSL"
    },
    {
        "id": 44990,
        "applicationDocumentDetailsList": [
            {
                "id": 30149,
                "activeStatus": "A",
                "modifiedBy": "madhya_user",
                "modifiedDate": "2026-03-13T10:44:45.847",
                "application": 44990,
                "documentType": 54,
                "submittedDate": "2026-03-13",
                "filePath": "madhya_user/2026-03-13/new bod member_FRJ_1773377974866.pdf",
                "encryptedId": "986e08f0820016669440564c2ec524b2484d82cd2030c7bb346c50fb4b6a756346c8c3b3d68d42fed07ffe0c2f5e86d58617ca8f9acdaabd224fd97ceeb2bc18",
                "fileUrl": "https://www.nepalstock.com.np/api/nots/security/fetchFiles?fileLocation=madhya_user/2026-03-13/new%20bod%20member_FRJ_1773377974866.pdf"
            }
        ],
        "newsHeadline": "New Director Welcomed [MBJC] ",
        "newsBody": "<p>During the company's 390th board meeting held on 2082/11/28 (Evening), Mr. Fanendra Raj Joshi (BOD Member from Chilime Jalavidyut Co. Ltd.) was inducted as a new Director. The board currently comprises 9 (nine) members representing Chilime, the NEA, and the general public.</p>",
        "addedDate": "2026-03-13T10:44:45.84",
        "newsSource": "390th BOD meeting dated 2082.11.28",
        "modifiedDate": "2026-03-13T11:37:15.13",
        "approvedDate": null,
        "symbol": "MBJC"
    },
    {
        "id": 44989,
        "applicationDocumentDetailsList": [
            {
                "id": 30148,
                "activeStatus": "A",
                "modifiedBy": "ili_user",
                "modifiedDate": "2026-03-13T08:02:08.6",
                "application": 44989,
                "documentType": 54,
                "submittedDate": "2026-03-13",
                "filePath": "IME_Life_Insurance_Company_Limited/Company News/2026-03-13/Reformation of Audit Committee Letter to NEPSE_1773368185013.pdf",
                "encryptedId": "8554e44fe21f72889cd0dc086527a448434812409ba9028292b4b712d500691f58ff0b52acb39ec7b7a3904f5e0b49467814d9638280fab5326ff8de2f2f6cff",
                "fileUrl": "https://www.nepalstock.com.np/api/nots/security/fetchFiles?fileLocation=IME_Life_Insurance_Company_Limited/Company%20News/2026-03-13/Reformation%20of%20Audit%20Committee%20Letter%20to%20NEPSE_1773368185013.pdf"
            }
        ],
        "newsHeadline": "Re-Formation Of Audit Committee [ILI] ",
        "newsBody": "<p>Dear Sir/Madam,</p><p></p><p>Please do find the letter regarding reformation of Audit Committee. </p><p></p><p>WBR </p><p>Prakash Neupane </p><p>Company Secretary</p>",
        "addedDate": "2026-03-13T08:02:08.59",
        "newsSource": "Board Meeting (Re-Formation Of Audit Committee)",
        "modifiedDate": "2026-03-13T09:35:04.87",
        "approvedDate": null,
        "symbol": "ILI"
    },
    {
        "id": 44986,
        "applicationDocumentDetailsList": [
            {
                "id": 30145,
                "activeStatus": "A",
                "modifiedBy": "ntc_user",
                "modifiedDate": "2026-03-12T16:16:18.683",
                "application": 44986,
                "documentType": 54,
                "submittedDate": "2026-03-12",
                "filePath": "ntc_user/2026-03-12/BOD Change_Reena Dangol_2082-11-27_1773311469749.pdf",
                "encryptedId": "7b2b2326015184568abebd012b8e45719f2774642ec1c8694999d883d159e829c5e7b52ddf5e0b9b5f1f969dee56963dcd34a70d0143d0891677b8a9b0f351a0",
                "fileUrl": "https://www.nepalstock.com.np/api/nots/security/fetchFiles?fileLocation=ntc_user/2026-03-12/BOD%20Change_Reena%20Dangol_2082-11-27_1773311469749.pdf"
            }
        ],
        "newsHeadline": "Change in BOD [NTC] ",
        "newsBody": "",
        "addedDate": "2026-03-12T16:16:18.68",
        "newsSource": "BOD and MOCIT",
        "modifiedDate": "2026-03-12T16:19:27.237",
        "approvedDate": null,
        "symbol": "NTC"
    },
    {
        "id": 44958,
        "applicationDocumentDetailsList": [
            {
                "id": 30118,
                "activeStatus": "A",
                "modifiedBy": "mkjc_user",
                "modifiedDate": "2026-03-11T16:55:32.403",
                "application": 44958,
                "documentType": 54,
                "submittedDate": "2026-03-11",
                "filePath": "mkjc_user/2026-03-11/Resignation of Chairman_1773227215193.pdf",
                "encryptedId": "ad2478cbb97f2f2c1a589b1312b81699ce177aa47f4f7bdad74e5a38d4659bcf60c98ef657144438c8dfa20b038d422718fc0ac36ddee4dfaca6842ec7d80e51",
                "fileUrl": "https://www.nepalstock.com.np/api/nots/security/fetchFiles?fileLocation=mkjc_user/2026-03-11/Resignation%20of%20Chairman_1773227215193.pdf"
            }
        ],
        "newsHeadline": "Resignation of Chairman [MKJC] ",
        "newsBody": "<p>\u0915\u092e\u094d\u092a\u0928\u0940\u0915\u094b \u0905\u0927\u094d\u092f\u0915\u094d\u0937 \u0924\u0925\u093e \u0938\u0902\u091a\u093e\u0932\u0915 \u0938\u092e\u093f\u0924\u093f\u0915\u094b \u092a\u0926\u092c\u093e\u091f \u0930\u093e\u091c\u093f\u0928\u093e\u092e\u093e \u0938\u094d\u0935\u0940\u0915\u0943\u0924 \u092d\u0908  \u0938\u094b \u0930\u093f\u0915\u094d\u0924 \u0938\u0902\u091a\u093e\u0932\u0915 \u092a\u0926\u092e\u093e \u0928\u092f\u093e\u0901 \u0938\u0902\u091a\u093e\u0932\u0915 \u0928\u093f\u092f\u0941\u0915\u094d\u0924\u093f \u0917\u0930\u093f\u090f\u0915\u094b \u092c\u093e\u0930\u0947 \u0964</p>",
        "addedDate": "2026-03-11T16:55:32.4",
        "newsSource": "Mailung Khola Jal Vidhyut Company Limited",
        "modifiedDate": "2026-03-12T08:11:43.62",
        "approvedDate": null,
        "symbol": "MKJC"
    },
    {
        "id": 44957,
        "applicationDocumentDetailsList": [
            {
                "id": 30117,
                "activeStatus": "A",
                "modifiedBy": "dlbs_user",
                "modifiedDate": "2026-03-11T16:46:11.923",
                "application": 44957,
                "documentType": 54,
                "submittedDate": "2026-03-11",
                "filePath": "Dhaulagiri_laghubitta_Sanstha_Limited/Company News/2026-03-11/sebon_faglun 27 divident_1773226843932.pdf",
                "encryptedId": "2cf138cda0440217f5629cc85babdb22f671fc2fb830766d55b02f0636f4af842e5695c83bb41402d1729d934b9617a0f749c969f108bc885b88d7517da33bd3",
                "fileUrl": "https://www.nepalstock.com.np/api/nots/security/fetchFiles?fileLocation=Dhaulagiri_laghubitta_Sanstha_Limited/Company%20News/2026-03-11/sebon_faglun%2027%20divident_1773226843932.pdf"
            }
        ],
        "newsHeadline": "Divedend Declaration of DLBS [DLBS] ",
        "newsBody": "Dividend Declaration of DLBS\nFiscal Year: 2081-2082",
        "addedDate": "2026-03-11T16:46:11.92",
        "newsSource": "Baord Meeting",
        "modifiedDate": "2026-03-12T08:11:20.05",
        "approvedDate": null,
        "symbol": "DLBS"
    },
    {
        "id": 44955,
        "applicationDocumentDetailsList": [
            {
                "id": 30115,
                "activeStatus": "A",
                "modifiedBy": "rlfl_user",
                "modifiedDate": "2026-03-11T15:57:20.937",
                "application": 44955,
                "documentType": 54,
                "submittedDate": "2026-03-11",
                "filePath": "rlfl_user/2026-03-11/rajinama Kush sir_1773223903514.pdf",
                "encryptedId": "fff46700db562f1e8761f34fa0e8e3a57d35498c254931bf14e7883b7bc99669a9c9530f85720d58377a29adc66d1cf282d0727023910cacefaa46d7cbd6f3e6",
                "fileUrl": "https://www.nepalstock.com.np/api/nots/security/fetchFiles?fileLocation=rlfl_user/2026-03-11/rajinama%20Kush%20sir_1773223903514.pdf"
            }
        ],
        "newsHeadline": "\u0930\u093e\u091c\u0940\u0928\u093e\u092e\u093e \u0938\u094d\u0935\u0940\u0915\u0943\u0924\u0940 \u092d\u090f\u0915\u094b \u091c\u093e\u0928\u0915\u093e\u0930\u0940 \u0938\u092e\u094d\u092c\u0928\u094d\u0927\u092e\u093e \u0964  [RLFL] ",
        "newsBody": "<p>\u092f\u0938 \u0938\u0902\u0938\u094d\u0925\u093e\u0915\u093e \u0938\u0902\u091a\u093e\u0932\u0915 \u0938\u092e\u093f\u0924\u093f\u0915\u093e \u0905\u0927\u094d\u092f\u0915\u094d\u0937 \u0936\u094d\u0930\u0940 \u0915\u0941\u0936 \u092a\u094d\u0930\u0938\u093e\u0926 \u092e\u0932\u094d\u0932\u0940\u091c\u094d\u092f\u0942\u0932\u0947 \u092f\u0938 \u0938\u0902\u0938\u094d\u0925\u093e\u0915\u094b \u0938\u0902\u091a\u093e\u0932\u0915 \u0924\u0925\u093e \u0938\u0902\u091a\u093e\u0932\u0915 \u0938\u092e\u093f\u0924\u093f\u0915\u094b \u0905\u0927\u094d\u092f\u0915\u094d\u0937 \u092a\u0926\u092c\u093e\u091f \u0926\u093f\u0928\u0941 \u092d\u090f\u0915\u094b \u0930\u093e\u091c\u0940\u0928\u093e\u092e\u093e \u092f\u0938 \u0938\u0902\u0938\u094d\u0925\u093e\u0915\u094b \u0938\u0902\u091a\u093e\u0932\u0915 \u0938\u092e\u093f\u0924\u093f\u0915\u094b \u092e\u093f\u0924\u093f \u0968\u0966\u096e\u0968/\u0967\u0967/\u0968\u096d \u0917\u0924\u0947 \u0926\u093f\u0928\u0915\u094b \u0969\u0903\u0966\u0966 \u092c\u091c\u0947 \u092c\u0938\u0947\u0915\u094b \u092c\u0948\u0920\u0915\u0932\u0947 \u0938\u094d\u0935\u0940\u0915\u0943\u0924\u0940 \u0917\u0930\u0947\u0915\u094b \u0935\u094d\u092f\u0939\u094b\u0930\u093e \u091c\u093e\u0928\u0915\u093e\u0930\u0940\u0915\u094b \u0932\u093e\u0917\u093f \u0905\u0928\u0941\u0930\u094b\u0927 \u091b \u0964</p>",
        "addedDate": "2026-03-11T15:57:20.93",
        "newsSource": "RFL",
        "modifiedDate": "2026-03-11T15:58:30.477",
        "approvedDate": null,
        "symbol": "RLFL"
    },
    {
        "id": 44935,
        "applicationDocumentDetailsList": [
            {
                "id": 30088,
                "activeStatus": "A",
                "modifiedBy": "nlic_user",
                "modifiedDate": "2026-03-09T10:14:19.79",
                "application": 44935,
                "documentType": 54,
                "submittedDate": "2026-03-09",
                "filePath": "nlic_user/2026-03-09/Disclosure to NEPSE _1773030554204.pdf",
                "encryptedId": "f48cc5d5cb29d206c90a5a4bf7e3764614ff8621973008e1cb00a7ddeec169fcd4f2ff421cc6e0c897bcf51011627a4946de95059c50b8c98086de5ce278193f",
                "fileUrl": "https://www.nepalstock.com.np/api/nots/security/fetchFiles?fileLocation=nlic_user/2026-03-09/Disclosure%20to%20NEPSE%20_1773030554204.pdf"
            }
        ],
        "newsHeadline": "Director's Resignation & new appointment of Director  [NLIC] ",
        "newsBody": "<p>410th Board Meeting (2082/11/24) has accepted the resignation of Director Mr. Govind Lal Sanghai and appointed to Mr. Purushottam Lal Sanghai as Director in that vacant position. Also, 411th Board Meeting held on 2082/11/25 (9 am) has appointed to Mr. Purushottam Lal Sanghai as the Chairman of the Company.</p>",
        "addedDate": "2026-03-09T10:14:19.78",
        "newsSource": "NLIC",
        "modifiedDate": "2026-03-09T10:15:34.233",
        "approvedDate": null,
        "symbol": "NLIC"
    },
    {
        "id": 44932,
        "applicationDocumentDetailsList": [
            {
                "id": 30085,
                "activeStatus": "A",
                "modifiedBy": "fowad_user",
                "modifiedDate": "2026-03-08T14:04:20.907",
                "application": 44932,
                "documentType": 54,
                "submittedDate": "2026-03-08",
                "filePath": "fowad_user/2026-03-08/About Dividend_1772957913778.pdf",
                "encryptedId": "96a71c1dcc424eb7e6da8c701e06f6ba6fc937e39db4dfa45b0927ba4fdfd016263e1b93b871e98e2a211e1b6bd3714693724b5eff9d7527eb13e4cd33e02679",
                "fileUrl": "https://www.nepalstock.com.np/api/nots/security/fetchFiles?fileLocation=fowad_user/2026-03-08/About%20Dividend_1772957913778.pdf"
            }
        ],
        "newsHeadline": "About Dividend [FOWAD] ",
        "newsBody": "Dividend Declaration of FOWAD\nFiscal Year: 2081-2082",
        "addedDate": "2026-03-08T14:04:20.87",
        "newsSource": "0",
        "modifiedDate": "2026-03-09T08:59:42.897",
        "approvedDate": null,
        "symbol": "FOWAD"
    },
    {
        "id": 44911,
        "applicationDocumentDetailsList": [
            {
                "id": 30063,
                "activeStatus": "A",
                "modifiedBy": "unlb_user",
                "modifiedDate": "2026-03-02T13:06:18.963",
                "application": 44911,
                "documentType": 54,
                "submittedDate": "2026-03-02",
                "filePath": "Unique_Nepal_Laghubitta_Bittiya_Sanstha_Limited/Company News/2026-03-02/FINAL MINUTE of 7th AGM with Annexes082-11-13_1772436075008.pdf",
                "encryptedId": "ea5380e6d34aa05af54917476e6b266e55f6dbcdc0194d9b1b430803de79a3710ec32179822b8e5aaf3e272ccecea59a07ef74db530d962e4cb6a757962ec961",
                "fileUrl": "https://www.nepalstock.com.np/api/nots/security/fetchFiles?fileLocation=Unique_Nepal_Laghubitta_Bittiya_Sanstha_Limited/Company%20News/2026-03-02/FINAL%20MINUTE%20of%207th%20AGM%20with%20Annexes082-11-13_1772436075008.pdf"
            }
        ],
        "newsHeadline": "7th AGM Minute [UNLB] ",
        "newsBody": "",
        "addedDate": "2026-03-02T13:06:18.96",
        "newsSource": "UNLBSL",
        "modifiedDate": "2026-03-03T10:02:32.393",
        "approvedDate": null,
        "symbol": "UNLB"
    },
    {
        "id": 44908,
        "applicationDocumentDetailsList": [
            {
                "id": 30060,
                "activeStatus": "A",
                "modifiedBy": "prin_user",
                "modifiedDate": "2026-03-02T10:35:00.99",
                "application": 44908,
                "documentType": 54,
                "submittedDate": "2026-03-02",
                "filePath": "prin_user/2026-03-02/prin-nepse_1772426946562.pdf",
                "encryptedId": "cd95b26847c56ef6b3693d2a99fcc69361c67ece6219fdb12edc66b905c84ff1691e5c3101fd555c11d49cc362fac95afb86fe8ba49d23e508dfb39817add919",
                "fileUrl": "https://www.nepalstock.com.np/api/nots/security/fetchFiles?fileLocation=prin_user/2026-03-02/prin-nepse_1772426946562.pdf"
            }
        ],
        "newsHeadline": "Dividend Declaration of Prabhu Insurance Limited  [PRIN] ",
        "newsBody": "<p>Dividend Declaration of Prabhu Insurance Limited (PRIN) Fiscal Year: 2081-2082 Cash Dividend: 0.4679% Bonus Shares: 8.7%</p>",
        "addedDate": "2026-03-02T10:35:00.97",
        "newsSource": "459th Board Meeting",
        "modifiedDate": "2026-03-03T10:01:38.66",
        "approvedDate": null,
        "symbol": "PRIN"
    },
    {
        "id": 44905,
        "applicationDocumentDetailsList": [
            {
                "id": 30057,
                "activeStatus": "A",
                "modifiedBy": "nsewa_user",
                "modifiedDate": "2026-03-01T16:44:52.147",
                "application": 44905,
                "documentType": 54,
                "submittedDate": "2026-03-01",
                "filePath": "nsewa_user/2026-03-01/Dividend_Cover_Letter_1772362762535.pdf",
                "encryptedId": "fdfaa2aa05daad2c38801255e19d083e1177dd90f7f1f02c20f4c7b6589b66cfc8ad43d296f47fba25cd55b59a53f056e1230aa41fcd5a007afb951a8df7852f",
                "fileUrl": "https://www.nepalstock.com.np/api/nots/security/fetchFiles?fileLocation=nsewa_user/2026-03-01/Dividend_Cover_Letter_1772362762535.pdf"
            }
        ],
        "newsHeadline": "Notice related to dividend and submission of Financial report for 2081/82 to Nepal Rastra Bank for AGM Approval. [WNLB] [WNLB] ",
        "newsBody": "",
        "addedDate": "2026-03-01T16:44:52.14",
        "newsSource": "Wnlb",
        "modifiedDate": "2026-03-03T10:00:03.66",
        "approvedDate": null,
        "symbol": "WNLB"
    },
    {
        "id": 44896,
        "applicationDocumentDetailsList": [
            {
                "id": 30052,
                "activeStatus": "A",
                "modifiedBy": "sindu_user",
                "modifiedDate": "2026-02-27T16:10:01.853",
                "application": 44896,
                "documentType": 54,
                "submittedDate": "2026-02-27",
                "filePath": "sindu_user/2026-02-27/Letter to NEPSE_1772187840830.pdf",
                "encryptedId": "974983b5ed7ba77116d5f2258b30a77baac6cc06d3f7a6445a36d560bb176a9f44e07260c57c27d9664503035b0c6c49a5c1d89097f7ab8ce2472d597abe2696",
                "fileUrl": "https://www.nepalstock.com.np/api/nots/security/fetchFiles?fileLocation=sindu_user/2026-02-27/Letter%20to%20NEPSE_1772187840830.pdf"
            }
        ],
        "newsHeadline": "Cancellation of 16 th AGM [SINDU] ",
        "newsBody": "<p>Cancellation of 16th AGM</p>",
        "addedDate": "2026-02-27T16:10:01.85",
        "newsSource": "BOD Meeting",
        "modifiedDate": "2026-03-01T10:01:00.647",
        "approvedDate": null,
        "symbol": "SINDU"
    },
    {
        "id": 44894,
        "applicationDocumentDetailsList": [
            {
                "id": 30050,
                "activeStatus": "A",
                "modifiedBy": "ushl_user",
                "modifiedDate": "2026-02-27T15:04:46.993",
                "application": 44894,
                "documentType": 54,
                "submittedDate": "2026-02-27",
                "filePath": "ushl_user/2026-02-27/Nepse_1772183982322.pdf",
                "encryptedId": "3dfd0a58680595c0078a558b0ccd08bd58dd408ba2c02a302a3f8fa00e0f3422353384e4fafbeee60f75c60198feedfed4a4608aae3d7f8d83af37a62951543c",
                "fileUrl": "https://www.nepalstock.com.np/api/nots/security/fetchFiles?fileLocation=ushl_user/2026-02-27/Nepse_1772183982322.pdf"
            }
        ],
        "newsHeadline": "Company Secretary Replacement [USHL] ",
        "newsBody": "",
        "addedDate": "2026-02-27T15:04:46.99",
        "newsSource": "68th Board Meeting Decision",
        "modifiedDate": "2026-03-01T10:00:13.19",
        "approvedDate": null,
        "symbol": "USHL"
    },
    {
        "id": 45004,
        "applicationDocumentDetailsList": [
            {
                "id": 30155,
                "activeStatus": "A",
                "modifiedBy": "sindu_user",
                "modifiedDate": "2026-03-13T16:23:35.227",
                "application": 45004,
                "documentType": 54,
                "submittedDate": "2026-03-13",
                "filePath": "sindu_user/2026-03-13/NEPSE_1773398295081.pdf",
                "encryptedId": "5d68567db12c5fb919a34e83a1cc055a64d17dbd574f7639b61ec063ae29939bcc9983dc66e42c01994fc6a0a37a3da375eb54306aadb351f2cde0511f9617bc",
                "fileUrl": "https://www.nepalstock.com.np/api/nots/security/fetchFiles?fileLocation=sindu_user/2026-03-13/NEPSE_1773398295081.pdf"
            }
        ],
        "newsHeadline": "Appointment of Directors and Auditor [SINDU] ",
        "newsBody": "<p>Completion of 16th AGM and appointment of public directors and external auditor for F.Y. 2082/83</p>",
        "addedDate": "2026-03-13T16:23:35.22",
        "newsSource": "16th AGM",
        "modifiedDate": "2026-03-15T10:12:32.783",
        "approvedDate": null,
        "symbol": "SINDU"
    },
    {
        "id": 45001,
        "applicationDocumentDetailsList": [
            {
                "id": 30152,
                "activeStatus": "A",
                "modifiedBy": "ntc_user",
                "modifiedDate": "2026-03-13T14:00:09.683",
                "application": 45001,
                "documentType": 54,
                "submittedDate": "2026-03-13",
                "filePath": "ntc_user/2026-03-13/Auditor Niyukti_Letter to OCR_2082-11-28_1773389668566.pdf",
                "encryptedId": "5557a6ee4e156390e6fc9d78fcce06b64d5d031beace0654aaaa59d599eec1e745df6699137fb5ec17d270d4914d42cad4d993b2ea79b9d21686b1effbd2efb0",
                "fileUrl": "https://www.nepalstock.com.np/api/nots/security/fetchFiles?fileLocation=ntc_user/2026-03-13/Auditor%20Niyukti_Letter%20to%20OCR_2082-11-28_1773389668566.pdf"
            }
        ],
        "newsHeadline": "Appointment of Auditors [NTC] ",
        "newsBody": "",
        "addedDate": "2026-03-13T14:00:09.68",
        "newsSource": "AGM and BOD",
        "modifiedDate": "2026-03-15T10:11:48.397",
        "approvedDate": null,
        "symbol": "NTC"
    },
    {
        "id": 45014,
        "applicationDocumentDetailsList": [
            {
                "id": 30164,
                "activeStatus": "A",
                "modifiedBy": "smh_user",
                "modifiedDate": "2026-03-15T15:11:59.563",
                "application": 45014,
                "documentType": 54,
                "submittedDate": "2026-03-15",
                "filePath": "Supermai_Hydropower_Limited/Company News/2026-03-15/11th AGM Signed Minute Upload_1773566759664.pdf",
                "encryptedId": "55902b1973fb50ffc876502ad9f41df14ea2766a69051cb105bc74ea9b6e39a6e92a7588958a5cfa92733edc96ecff0cce50bfd91b4041b4a3c850eb38de7103",
                "fileUrl": "https://www.nepalstock.com.np/api/nots/security/fetchFiles?fileLocation=Supermai_Hydropower_Limited/Company%20News/2026-03-15/11th%20AGM%20Signed%20Minute%20Upload_1773566759664.pdf"
            }
        ],
        "newsHeadline": "AGM Minute of Supermai Hydropower Limited  [SMH] ",
        "newsBody": "<p>11th AGM Minute-Supermai Hydropower Limited</p>",
        "addedDate": "2026-03-15T15:11:59.56",
        "newsSource": "11th AGM of Supermai Hydropower Limited ",
        "modifiedDate": "2026-03-15T15:28:27.03",
        "approvedDate": null,
        "symbol": "SMH"
    },
    {
        "id": 45042,
        "applicationDocumentDetailsList": [
            {
                "id": 30184,
                "activeStatus": "A",
                "modifiedBy": "spdl_user",
                "modifiedDate": "2026-03-16T15:14:30.293",
                "application": 45042,
                "documentType": 54,
                "submittedDate": "2026-03-16",
                "filePath": "spdl_user/2026-03-16/19 Agm Minute_merged_1773653357010.pdf",
                "encryptedId": "5ed276c8cc0839523a2d050bad8a14b7a073c1873717056393bbd33fd1cf8a36988bec3d63a5d34360c1c36ddb1c506aa38f9be8bdb25e6d973d37698e5ebf6e",
                "fileUrl": "https://www.nepalstock.com.np/api/nots/security/fetchFiles?fileLocation=spdl_user/2026-03-16/19%20Agm%20Minute_merged_1773653357010.pdf"
            }
        ],
        "newsHeadline": "19th AGM Minute [SPDL] ",
        "newsBody": "",
        "addedDate": "2026-03-16T15:14:30.29",
        "newsSource": "AGM ",
        "modifiedDate": "2026-03-16T15:17:21.157",
        "approvedDate": null,
        "symbol": "SPDL"
    }
]